dag_manager/__init__.py
dag_manager/app.py
dag_manager/auth.py
dag_manager/config.py
dag_manager/exceptions.py
dag_manager/globals.py
dag_manager/blueprints/__init__.py
dag_manager/blueprints/dag_ids.py
dag_manager/blueprints/dags.py
dag_manager/util/__init__.py
dag_manager/util/lock.py
dag_manager-0.1.5a0.data/scripts/dmc
dag_receiver/__init__.py
dag_receiver/app.py
dag_receiver/config.py
dag_receiver/exceptions.py
dmc/__init__.py
dmc/dmc.py
dmc/exceptions.py
dmc/bin/__init__.py
dmc/bin/cli.py
dmc/bin/dmc
dag_manager-0.1.5a0.dist-info/METADATA
dag_manager-0.1.5a0.dist-info/WHEEL
dag_manager-0.1.5a0.dist-info/top_level.txt
dag_manager-0.1.5a0.dist-info/RECORD
